{
    "name": "distributor",
    "exclude": [
        ".\/node_modules"
    ],
    "tests": [
        "tests\/wpacceptance\/*Test.php"
    ],
    "enforce_clean_db": true,
    "bootstrap": "tests\/wpacceptance\/bootstrap.php",
    "environment_instructions": [
      "install wordpress where type is multisite and url is http://distributor.test",
      "add site where name is Site Two and url is http://distributor.test/two",
      "add site where name is Site Three and url is http://distributor.test/three",
      "activate plugin where name is distributor and active type is network",
      "enable theme where name is twentyseventeen"
    ],
    "project_path": "%WP_ROOT%/wp-content/plugins/distributor"
}
